{"cameraMode":{"drawMode":0,"name":"Shaded","section":"Shading Mode"},"sceneLighting":true,"audioPlay":false,"sceneViewState":{"m_AlwaysRefresh":false,"showFog":true,"showSkybox":true,"showFlares":true,"showImageEffects":true,"showParticleSystems":true,"showVisualEffectGraphs":true,"m_FxEnabled":true},"in2DMode":false,"pivot":{"x":91.2395248413086,"y":-808.1751708984375,"z":115.97369384765625},"rotation":{"x":-0.6843299865722656,"y":-0.005145166534930468,"z":0.004985547624528408,"w":-0.7292811274528503},"size":462.0543518066406,"orthographic":false}